[
    {
        "id":"er4534",
        "status":"Paid",
        "amount":4500,
        "date":"2015-01-01",
        "products":[{}, {}]
    },
    {
        "id":"er4784",
        "status":"Paid",
        "amount":4900,
        "date":"2015-01-01",
        "products":[{}, {}]
    },
    {
        "id":"er4334",
        "status":"Paid",
        "amount":6500,
        "date":"2015-01-01",
        "products":[{}, {}]
    },
    {
        "id":"er4594",
        "status":"Paid",
        "amount":2500,
        "date":"2015-01-01",
        "products":[{}, {}]
    }


]